omoment/__init__.py
omoment/obase.py
omoment/omean.py
omoment/omeanvar.py
omoment/ominmax.py
omoment/oreg.py
omoment/version.py
omoment-0.1.5.dist-info/LICENSE
omoment-0.1.5.dist-info/WHEEL
omoment-0.1.5.dist-info/METADATA
omoment-0.1.5.dist-info/RECORD
