Metadata-Version: 2.1
Name: omoment
Version: 0.1.5
Summary: OMoment package calculates moments of statistical distributions (means, variances, covariance) in online or
Keywords: statistics,mean,variance,distributed,estimation,efficient,additive
Author-email: Tomas Protivinsky <tomas.protivinsky@gmail.com>
Requires-Python: >=3.7
Classifier: Development Status :: 3 - Alpha
Classifier: License :: OSI Approved :: MIT License
Classifier: Natural Language :: English
Classifier: Operating System :: OS Independent
Classifier: Programming Language :: Python
Classifier: Programming Language :: Python :: 3.7
Classifier: Programming Language :: Python :: 3.8
Classifier: Programming Language :: Python :: 3.9
Requires-Dist: numpy >= 1.19.0
Requires-Dist: pandas >= 1.1.0
Requires-Dist: pytest >= 7.0.0 ; extra == "dev"
Requires-Dist: pytest-cov >= 3.0.0 ; extra == "dev"
Project-URL: Documentation, https://protivinsky.github.io/omoment
Project-URL: Homepage, https://github.com/protivinsky/omoment
Provides-Extra: dev
